{
  "20230612_002623.jpg": "07/12/2023",
  "20230612_002849.jpg": "07/12/2023",
  "20230612_003038.jpg": "07/12/2023",
  "20230612_003040.jpg": "07/12/2023",
  "20230612_012124.jpg": "07/12/2023",
  "20230614_232029.jpg": "07/12/2023",
  "20230728_224313.jpg": "07/12/2023",
  "20230728_224316.jpg": "07/12/2023",
  "Screenshot (100).png": "17/11/2023",
  "Screenshot (101).png": "18/11/2023",
  "Screenshot (102).png": "19/11/2023",
  "Screenshot (103).png": "20/11/2023",
  "Screenshot (104).png": "21/11/2023",
  "Screenshot (105).png": "21/11/2023",
  "Screenshot (106).png": "21/11/2023",
  "Screenshot (107).png": "22/11/2023",
  "Screenshot (108).png": "25/11/2023",
  "Screenshot (109).png": "26/11/2023",
  "Screenshot (110).png": "28/11/2023",
  "Screenshot (111).png": "28/11/2023",
  "Screenshot (112).png": "28/11/2023",
  "Screenshot (114).png": "01/12/2023",
  "Screenshot (115).png": "01/12/2023",
  "Screenshot (116).png": "03/12/2023",
  "Screenshot (117).png": "04/12/2023",
  "Screenshot (118).png": "10/12/2023",
  "Screenshot (119).png": "10/12/2023",
  "Screenshot (120).png": "12/12/2023",
  "Screenshot (121).png": "12/12/2023",
  "Screenshot (123).png": "13/12/2023",
  "Screenshot (124).png": "14/12/2023",
  "Screenshot (125).png": "14/12/2023",
  "Screenshot (126).png": "14/12/2023",
  "Screenshot (127).png": "14/12/2023",
  "Screenshot (128).png": "15/12/2023",
  "Screenshot (129).png": "15/12/2023",
  "Screenshot (130).png": "18/12/2023",
  "Screenshot (131).png": "18/12/2023",
  "Screenshot (132).png": "19/12/2023",
  "Screenshot (133).png": "19/12/2023",
  "Screenshot (134).png": "19/12/2023",
  "Screenshot (135).png": "20/12/2023",
  "Screenshot (136).png": "21/12/2023",
  "Screenshot (137).png": "21/12/2023",
  "Screenshot (138).png": "21/12/2023",
  "Screenshot (139).png": "21/12/2023",
  "Screenshot (140).png": "23/12/2023",
  "Screenshot (15).png": "27/06/2023",
  "Screenshot (16).png": "27/06/2023",
  "Screenshot (17).png": "27/06/2023",
  "Screenshot (18).png": "28/06/2023",
  "Screenshot (19).png": "28/06/2023",
  "Screenshot (20).png": "28/06/2023",
  "Screenshot (21).png": "28/06/2023",
  "Screenshot (22).png": "28/06/2023",
  "Screenshot (23).png": "29/06/2023",
  "Screenshot (24).png": "08/07/2023",
  "Screenshot (31).png": "17/07/2023",
  "Screenshot (32).png": "17/07/2023",
  "Screenshot (33).png": "22/07/2023",
  "Screenshot (34).png": "22/07/2023",
  "Screenshot (35).png": "22/07/2023",
  "Screenshot (37).png": "22/07/2023",
  "Screenshot (40).png": "25/07/2023",
  "Screenshot (63).png": "21/08/2023",
  "Screenshot (69).png": "30/09/2023",
  "Screenshot (72).png": "06/10/2023",
  "Screenshot (73).png": "07/10/2023",
  "Screenshot (74).png": "09/10/2023",
  "Screenshot (75).png": "10/10/2023",
  "Screenshot (76).png": "12/10/2023",
  "Screenshot (78).png": "24/10/2023",
  "Screenshot (79).png": "29/10/2023",
  "Screenshot (80).png": "29/10/2023",
  "Screenshot (81).png": "29/10/2023",
  "Screenshot (82).png": "31/10/2023",
  "Screenshot (83).png": "31/10/2023",
  "Screenshot (84).png": "02/11/2023",
  "Screenshot (85).png": "04/11/2023",
  "Screenshot (86).png": "05/11/2023",
  "Screenshot (91).png": "06/11/2023",
  "Screenshot (92).png": "06/11/2023",
  "Screenshot (94).png": "06/11/2023",
  "Screenshot (95).png": "09/11/2023",
  "Screenshot (96).png": "14/11/2023",
  "Screenshot (97).png": "14/11/2023",
  "Screenshot (98).png": "16/11/2023",
  "Screenshot (99).png": "16/11/2023",
  "Screenshot 2023-08-01 104935.png": "01/08/2023",
  "Screenshot 2023-08-01 105103.png": "01/08/2023",
  "Screenshot_20230928_000050_Meet.jpg": "07/12/2023",
  "Screenshot_20230928_000052_Meet.jpg": "07/12/2023",
  "Screenshot_20231004_233635_WhatsApp.jpg": "07/12/2023",
  "Screenshot_20231024_225721_Meet.jpg": "07/12/2023",
  "Screenshot_20231110_225218_Meet.jpg": "23/12/2023",
  "Screenshot_20231120_231053_Meet.jpg": "07/12/2023",
  "Screenshot_20231122_232640_Meet.jpg": "23/12/2023",
  "Screenshot_20231124_002045_WhatsApp.jpg": "23/12/2023",
  "Screenshot_20231201_001847_Meet.jpg": "23/12/2023",
  "Screenshot_20231205_224914_Meet.jpg": "23/12/2023",
  "Screenshot_20231206_230403_Meet.jpg": "23/12/2023",
  "Screenshot_20231207_171400_WhatsApp.jpg": "23/12/2023",
  "Screenshot_20231207_221619_Meet.jpg": "23/12/2023",
  "Screenshot_20231207_222139_Meet.jpg": "23/12/2023"
}